sap10calcs/__init__.py
sap10calcs/_generate_auto_classes.py
sap10calcs/classes_RdSAP_Schema_21_0_0.py
sap10calcs/classes_SAP_Schema_19_1_0.py
sap10calcs/functions.py
sap10calcs/instances.py
sap10calcs-0.0.3.dist-info/LICENSE
sap10calcs-0.0.3.dist-info/METADATA
sap10calcs-0.0.3.dist-info/WHEEL
sap10calcs-0.0.3.dist-info/top_level.txt
sap10calcs-0.0.3.dist-info/RECORD
