Metadata-Version: 2.1
Name: sap10calcs
Version: 0.0.3
Summary: SAP 10.2 energy calculation method in Python
Author-email: Steven Firth <s.k.firth@lboro.ac.uk>
Project-URL: Homepage, https://github.com/stevenkfirth/sap10calcs
Classifier: Programming Language :: Python :: 3
Classifier: License :: OSI Approved :: MIT License
Classifier: Operating System :: OS Independent
Requires-Python: >=3.6
License-File: LICENSE
Requires-Dist: requests
Requires-Dist: lxml
